{
  "_class": "symbolInstance",
  "booleanOperation": 0,
  "clippingMaskMode": 0,
  "do_objectID": "1F0B7627-F44E-4614-BAA4-569FC2FBB2E9",
  "exportOptions": {
    "_class": "exportOptions",
    "do_objectID": "50E867A2-AE30-4A1F-8086-00D873E27049",
    "exportFormats": [
    ],
    "includedLayerIds": [
    ],
    "layerOptions": 0,
    "shouldTrim": false
  },
  "frame": {
    "_class": "rect",
    "constrainProportions": false,
    "do_objectID": "639F3E79-70C1-424E-9A5E-4D13F944D549",
    "height": 50,
    "width": 3.057219862122187,
    "x": 0,
    "y": 99
  },
  "hasClippingMask": false,
  "horizontalSpacing": 0,
  "isFixedToViewport": false,
  "isFlippedHorizontal": false,
  "isFlippedVertical": false,
  "isLocked": false,
  "isVisible": true,
  "layerListExpandedType": 0,
  "name": "indicator 3",
  "nameIsFixed": true,
  "overrideValues": [
  ],
  "resizingConstraint": 63,
  "resizingType": 0,
  "rotation": 0,
  "scale": 1,
  "shouldBreakMaskChain": false,
  "style": {
    "_class": "style",
    "do_objectID": "9EF22437-817C-4CC4-A3E9-F915E268B858",
    "endMarkerType": 0,
    "miterLimit": 10,
    "startMarkerType": 0,
    "windingRule": 1
  },
  "symbolID": "090060A7-1F85-4A62-8E3F-80043FB46D88",
  "verticalSpacing": 0
}