{
  "_class": "symbolInstance",
  "booleanOperation": 0,
  "clippingMaskMode": 0,
  "do_objectID": "8C8CEE9A-7E9B-4339-885B-EF874B7B6564",
  "exportOptions": {
    "_class": "exportOptions",
    "do_objectID": "054CB6EC-FA3A-41BA-8DFD-8D3A3FBA04C4",
    "exportFormats": [
    ],
    "includedLayerIds": [
    ],
    "layerOptions": 0,
    "shouldTrim": false
  },
  "frame": {
    "_class": "rect",
    "constrainProportions": false,
    "do_objectID": "4DD77604-1FC7-461D-BECE-A35885EF6DCB",
    "height": 4,
    "width": 208.0734120315914,
    "x": 24,
    "y": 46
  },
  "hasClippingMask": false,
  "horizontalSpacing": 0,
  "isFixedToViewport": false,
  "isFlippedHorizontal": false,
  "isFlippedVertical": false,
  "isLocked": false,
  "isVisible": true,
  "layerListExpandedType": 0,
  "name": "line 1",
  "nameIsFixed": true,
  "originalObjectID": "D8796EC1-6029-4DA9-854A-0260FBA4DEAA",
  "overrideValues": [
  ],
  "resizingConstraint": 58,
  "resizingType": 0,
  "rotation": 0,
  "scale": 1,
  "shouldBreakMaskChain": false,
  "style": {
    "_class": "style",
    "do_objectID": "D632A8ED-D0E8-42B7-AC15-C37039922FCA",
    "endMarkerType": 0,
    "miterLimit": 10,
    "startMarkerType": 0,
    "windingRule": 1
  },
  "symbolID": "13A29A8D-E54B-47EF-9479-360EB4F55F8C",
  "verticalSpacing": 0
}