{
  "_class": "shapePath",
  "booleanOperation": -1,
  "clippingMaskMode": 0,
  "do_objectID": "641199BB-D3B3-4D4C-8F81-38C37F2426F1",
  "edited": true,
  "exportOptions": {
    "_class": "exportOptions",
    "exportFormats": [
    ],
    "includedLayerIds": [
    ],
    "layerOptions": 0,
    "shouldTrim": false
  },
  "frame": {
    "_class": "rect",
    "constrainProportions": false,
    "height": 3,
    "width": 4,
    "x": 1,
    "y": 5
  },
  "hasClippingMask": false,
  "isClosed": true,
  "isFixedToViewport": false,
  "isFlippedHorizontal": false,
  "isFlippedVertical": false,
  "isLocked": false,
  "isVisible": true,
  "layerListExpandedType": 0,
  "name": "Path",
  "nameIsFixed": false,
  "pointRadiusBehaviour": 1,
  "points": [
    {
      "_class": "curvePoint",
      "cornerRadius": 0,
      "curveFrom": "{0.67348742326873279, 1}",
      "curveMode": 3,
      "curveTo": "{0.8141529015947323, 1}",
      "hasCurveFrom": true,
      "hasCurveTo": true,
      "point": "{0.72037591604406592, 1}"
    },
    {
      "_class": "curvePoint",
      "cornerRadius": 0,
      "curveFrom": "{0.57971043771806641, 0.95392659763689147}",
      "curveMode": 4,
      "curveTo": "{0.62659893049339954, 0.98848164940922267}",
      "hasCurveFrom": false,
      "hasCurveTo": true,
      "point": "{0.57971043771806641, 0.95392659763689147}"
    },
    {
      "_class": "curvePoint",
      "cornerRadius": 0,
      "curveFrom": "{0.007670825859001475, 0.55078432695969015}",
      "curveMode": 4,
      "curveTo": "{0.1389586056299344, 0.64293113168590765}",
      "hasCurveFrom": true,
      "hasCurveTo": false,
      "point": "{0.1389586056299344, 0.64293113168590765}"
    },
    {
      "_class": "curvePoint",
      "cornerRadius": 0,
      "curveFrom": "{0.11082550996473434, 0.0094218491931628446}",
      "curveMode": 2,
      "curveTo": "{-0.039217666916331717, 0.33193566573492395}",
      "hasCurveFrom": true,
      "hasCurveTo": true,
      "point": "{0.035803921524201331, 0.1706787574640434}"
    },
    {
      "_class": "curvePoint",
      "cornerRadius": 0,
      "curveFrom": "{0.42028956228193343, 0.043976900965494461}",
      "curveMode": 4,
      "curveTo": "{0.28900178251100056, -0.048169903760723047}",
      "hasCurveFrom": false,
      "hasCurveTo": true,
      "point": "{0.42028956228193343, 0.043976900965494461}"
    },
    {
      "_class": "curvePoint",
      "cornerRadius": 0,
      "curveFrom": "{0.99232917414099853, 0.44711917164269571}",
      "curveMode": 4,
      "curveTo": "{0.86104139437006555, 0.35497236691647821}",
      "hasCurveFrom": true,
      "hasCurveTo": false,
      "point": "{0.86104139437006555, 0.35497236691647821}"
    },
    {
      "_class": "curvePoint",
      "cornerRadius": 0,
      "curveFrom": "{0.90792988714539868, 0.94240824704611414}",
      "curveMode": 4,
      "curveTo": "{1.0392176669163318, 0.66596783286746197}",
      "hasCurveFrom": true,
      "hasCurveTo": true,
      "point": "{0.96419607847579847, 0.82722474113834277}"
    }
  ],
  "resizingConstraint": 63,
  "resizingType": 0,
  "rotation": 0,
  "shouldBreakMaskChain": false,
  "style": {
    "_class": "style",
    "endMarkerType": 0,
    "fills": [
      {
        "_class": "fill",
        "color": {
          "_class": "color",
          "alpha": 1,
          "blue": 0.9764705882352941,
          "green": 1,
          "red": 0.8823529411764706
        },
        "fillType": 0,
        "isEnabled": true,
        "noiseIndex": 0,
        "noiseIntensity": 0,
        "patternFillType": 1,
        "patternTileScale": 1
      }
    ],
    "miterLimit": 10,
    "startMarkerType": 0,
    "windingRule": 0
  }
}