{
  "_class": "symbolInstance",
  "booleanOperation": -1,
  "clippingMaskMode": 0,
  "do_objectID": "04A69BD2-041B-4E21-8D20-BEE21C39EE22",
  "exportOptions": {
    "_class": "exportOptions",
    "do_objectID": "592562F5-5C7F-4533-A074-5E4B19342B05",
    "exportFormats": [
    ],
    "includedLayerIds": [
    ],
    "layerOptions": 0,
    "shouldTrim": false
  },
  "frame": {
    "_class": "rect",
    "constrainProportions": false,
    "do_objectID": "DDB7D3E9-8894-4BA0-87E3-2C99DB212901",
    "height": 190,
    "width": 190,
    "x": 186,
    "y": 122
  },
  "hasClippingMask": false,
  "horizontalSpacing": 0,
  "isFixedToViewport": false,
  "isFlippedHorizontal": false,
  "isFlippedVertical": false,
  "isLocked": false,
  "isVisible": true,
  "layerListExpandedType": 0,
  "name": "Dual auth img",
  "nameIsFixed": true,
  "overrideValues": [
  ],
  "resizingConstraint": 63,
  "resizingType": 0,
  "rotation": 0,
  "scale": 1,
  "shouldBreakMaskChain": false,
  "style": {
    "_class": "style",
    "do_objectID": "173DC9A1-7327-413F-A26A-A0D1FE7FC09A",
    "endMarkerType": 0,
    "miterLimit": 10,
    "startMarkerType": 0,
    "windingRule": 1
  },
  "symbolID": "FF99942F-514A-4081-B728-B262262D6A86",
  "verticalSpacing": 0
}