{
  "_class": "symbolInstance",
  "booleanOperation": 0,
  "clippingMaskMode": 0,
  "do_objectID": "8B1E7073-EE6A-48AB-B004-E72032C2B329",
  "exportOptions": {
    "_class": "exportOptions",
    "do_objectID": "00F9528E-A7F7-4617-B341-C3EC71A726C2",
    "exportFormats": [
    ],
    "includedLayerIds": [
    ],
    "layerOptions": 0,
    "shouldTrim": false
  },
  "frame": {
    "_class": "rect",
    "constrainProportions": false,
    "do_objectID": "95925B18-1836-4BFE-85D3-90DB1BE5F9FF",
    "height": 50,
    "width": 135,
    "x": 26,
    "y": 70
  },
  "hasClippingMask": false,
  "horizontalSpacing": 0,
  "isFixedToViewport": false,
  "isFlippedHorizontal": false,
  "isFlippedVertical": false,
  "isLocked": false,
  "isVisible": true,
  "layerListExpandedType": 0,
  "name": "Tables/coza/Text/header/1line_L",
  "nameIsFixed": false,
  "overrideValues": [
    {
      "_class": "overrideValue",
      "do_objectID": "30D27A7C-B036-4FBE-AF4C-4A0ED1D2E8B9",
      "overrideName": "802AA283-323F-46F2-9102-67905E307818_stringValue",
      "value": "R800 000"
    }
  ],
  "resizingConstraint": 63,
  "resizingType": 0,
  "rotation": 0,
  "scale": 1,
  "shouldBreakMaskChain": false,
  "style": {
    "_class": "style",
    "do_objectID": "2127FB5C-1937-42A6-9332-35375252D8E9",
    "endMarkerType": 0,
    "miterLimit": 10,
    "startMarkerType": 0,
    "windingRule": 1
  },
  "symbolID": "BCCD2817-2CF4-42D2-85EA-5E29D0CFDD1B",
  "verticalSpacing": 0
}