{
  "_class": "symbolInstance",
  "booleanOperation": 0,
  "clippingMaskMode": 0,
  "do_objectID": "C2D95E18-98AA-4902-A7E2-D9872D4572BF",
  "exportOptions": {
    "_class": "exportOptions",
    "do_objectID": "A9EC5604-1404-4326-A612-71D870D61226",
    "exportFormats": [
    ],
    "includedLayerIds": [
    ],
    "layerOptions": 0,
    "shouldTrim": false
  },
  "frame": {
    "_class": "rect",
    "constrainProportions": false,
    "do_objectID": "A6BE9958-38C4-4261-A832-B4559557D234",
    "height": 50,
    "width": 155,
    "x": 566,
    "y": 327
  },
  "hasClippingMask": false,
  "horizontalSpacing": 0,
  "isFixedToViewport": false,
  "isFlippedHorizontal": false,
  "isFlippedVertical": false,
  "isLocked": false,
  "isVisible": true,
  "layerListExpandedType": 2,
  "name": "Tables/coza/Text/header/1line_L",
  "nameIsFixed": false,
  "overrideValues": [
    {
      "_class": "overrideValue",
      "overrideName": "1ABD0E87-445E-44B4-A2C1-2C5911BF226E_stringValue",
      "value": "Applicant ID\n/Passport #"
    }
  ],
  "resizingConstraint": 63,
  "resizingType": 0,
  "rotation": 0,
  "scale": 1,
  "shouldBreakMaskChain": false,
  "style": {
    "_class": "style",
    "do_objectID": "42072B21-3B0E-4412-ACCC-3DD98ACAD017",
    "endMarkerType": 0,
    "miterLimit": 10,
    "startMarkerType": 0,
    "windingRule": 1
  },
  "symbolID": "7441C4DB-38D2-448D-9011-A18373E58A12",
  "verticalSpacing": 0
}