{
  "_class": "group",
  "booleanOperation": 0,
  "clippingMaskMode": 0,
  "do_objectID": "1EF8456E-F090-4C6C-8954-188B879C0D66",
  "exportOptions": {
    "_class": "exportOptions",
    "exportFormats": [
    ],
    "includedLayerIds": [
    ],
    "layerOptions": 0,
    "shouldTrim": false
  },
  "frame": {
    "_class": "rect",
    "constrainProportions": false,
    "do_objectID": "F2777150-F239-47EF-8405-A5E195B1C8DA",
    "height": 25,
    "width": 976.0546075085324,
    "x": 0,
    "y": 0
  },
  "groupLayout": {
    "_class": "MSImmutableFreeformGroupLayout",
    "do_objectID": "9E142356-BDDF-4D1B-B84A-93AED89AEC28"
  },
  "hasClickThrough": false,
  "hasClippingMask": false,
  "isFixedToViewport": false,
  "isFlippedHorizontal": false,
  "isFlippedVertical": false,
  "isLocked": false,
  "isVisible": false,
  "layerListExpandedType": 1,
  "layers": [
    {
      "class": "shapePath",
      "id": "AF88C7C9-BC0E-47F9-9B68-056806F6183D"
    },
    {
      "class": "shapePath",
      "id": "B73A3457-2C14-4832-AF91-DEDF81F0FF73"
    },
    {
      "class": "shapePath",
      "id": "98C911C1-B125-4F92-8A2C-F59ABBF0DEF4"
    },
    {
      "class": "shapePath",
      "id": "9DB78618-F555-415E-B733-4ACB02A5493A"
    },
    {
      "class": "shapePath",
      "id": "A5446133-B3FD-4601-9817-506599F6FCE0"
    },
    {
      "class": "shapePath",
      "id": "81272E4A-FDDD-4688-92B7-FF8515F15419"
    },
    {
      "class": "shapePath",
      "id": "8ADB500F-2260-4CD8-A385-345C777E89AE"
    },
    {
      "class": "shapePath",
      "id": "B8322F1A-0DCF-4349-A719-1D2760BD7500"
    },
    {
      "class": "shapePath",
      "id": "6C28B87B-5B45-4F89-9015-78425966F788"
    },
    {
      "class": "shapePath",
      "id": "37CA2879-88A9-4CD8-80AD-BA0D7775658F"
    },
    {
      "class": "shapePath",
      "id": "EE98039A-6C7A-4D36-B75F-99514C76B5D5"
    }
  ],
  "name": "Lines",
  "nameIsFixed": true,
  "resizingConstraint": 63,
  "resizingType": 0,
  "rotation": 0,
  "shouldBreakMaskChain": false,
  "style": {
    "_class": "style",
    "contextSettings": {
      "_class": "graphicsContextSettings",
      "blendMode": 0,
      "do_objectID": "5AE944F7-8DFE-42F5-A31C-B58BBCBD54C6",
      "opacity": 0.09793931159420292
    },
    "do_objectID": "DAE534E1-ED96-4BED-8EA0-336726BBEB28",
    "endMarkerType": 0,
    "miterLimit": 10,
    "startMarkerType": 0,
    "windingRule": 1
  }
}