{
  "_class": "symbolInstance",
  "booleanOperation": 0,
  "clippingMaskMode": 0,
  "do_objectID": "32DF861A-695C-4778-8F1C-3FEE085281C7",
  "exportOptions": {
    "_class": "exportOptions",
    "exportFormats": [
    ],
    "includedLayerIds": [
    ],
    "layerOptions": 0,
    "shouldTrim": false
  },
  "frame": {
    "_class": "rect",
    "constrainProportions": false,
    "height": 25,
    "width": 65,
    "x": 0,
    "y": 500
  },
  "hasClippingMask": false,
  "horizontalSpacing": 0,
  "isFixedToViewport": false,
  "isFlippedHorizontal": false,
  "isFlippedVertical": false,
  "isLocked": false,
  "isVisible": true,
  "layerListExpandedType": 0,
  "name": "build/GridBlock",
  "nameIsFixed": true,
  "originalObjectID": "F219B2AF-9F64-49A8-9709-6F32DB4513D2",
  "overrideValues": [
    {
      "_class": "overrideValue",
      "overrideName": "E445CE0B-0BCC-489D-9F46-E767ABA5DBCB_stringValue",
      "value": "21"
    }
  ],
  "resizingConstraint": 63,
  "resizingType": 0,
  "rotation": 0,
  "scale": 1,
  "shouldBreakMaskChain": false,
  "style": {
    "_class": "style",
    "endMarkerType": 0,
    "miterLimit": 10,
    "startMarkerType": 0,
    "windingRule": 1
  },
  "symbolID": "8ECE6090-7488-4C24-A0D2-CFC4B863B643",
  "verticalSpacing": 0
}