{
  "_class": "symbolInstance",
  "booleanOperation": 0,
  "clippingMaskMode": 0,
  "do_objectID": "2A036CE9-A702-4F35-BE47-D6E1EC3977FE",
  "exportOptions": {
    "_class": "exportOptions",
    "exportFormats": [
    ],
    "includedLayerIds": [
    ],
    "layerOptions": 0,
    "shouldTrim": false
  },
  "frame": {
    "_class": "rect",
    "constrainProportions": false,
    "do_objectID": "E5729E25-5BA5-4D21-87B6-6E93E42B1DD2",
    "height": 50,
    "width": 200,
    "x": 1015,
    "y": 445
  },
  "hasClippingMask": false,
  "horizontalSpacing": 0,
  "isFixedToViewport": false,
  "isFlippedHorizontal": false,
  "isFlippedVertical": false,
  "isLocked": false,
  "isVisible": true,
  "layerListExpandedType": 0,
  "name": "Tables/coza/Text/header/1line_L Copy 32",
  "nameIsFixed": false,
  "overrideValues": [
    {
      "_class": "overrideValue",
      "overrideName": "7CFC81D0-17D2-439B-8A4F-8CCB936E1480_stringValue",
      "value": "nembol@hotmil.com"
    }
  ],
  "resizingConstraint": 63,
  "resizingType": 0,
  "rotation": 0,
  "scale": 1,
  "shouldBreakMaskChain": false,
  "style": {
    "_class": "style",
    "do_objectID": "5AA43AD4-1C9D-4625-AB9E-06C8A44A54FF",
    "endMarkerType": 0,
    "miterLimit": 10,
    "startMarkerType": 0,
    "windingRule": 1
  },
  "symbolID": "07FF4E2E-9349-4243-93AD-D0D2F89FB088",
  "verticalSpacing": 0
}