{
  "_class": "symbolInstance",
  "booleanOperation": 0,
  "clippingMaskMode": 0,
  "do_objectID": "A01DAA7C-C4C1-41C1-86EF-E08A716542A4",
  "exportOptions": {
    "_class": "exportOptions",
    "exportFormats": [
    ],
    "includedLayerIds": [
    ],
    "layerOptions": 0,
    "shouldTrim": false
  },
  "frame": {
    "_class": "rect",
    "constrainProportions": false,
    "do_objectID": "315BB674-7744-4835-9FC9-D8588D99D5FB",
    "height": 50,
    "width": 565,
    "x": 182,
    "y": 250
  },
  "hasClippingMask": false,
  "horizontalSpacing": 0,
  "isFixedToViewport": false,
  "isFlippedHorizontal": false,
  "isFlippedVertical": false,
  "isLocked": false,
  "isVisible": true,
  "layerListExpandedType": 0,
  "name": "text/H3/blk_l",
  "nameIsFixed": false,
  "overrideValues": [
    {
      "_class": "overrideValue",
      "overrideName": "EF70B9CF-9111-4F98-A75B-A403A178D581_symbolID",
      "value": ""
    },
    {
      "_class": "overrideValue",
      "overrideName": "D63F0BEE-ADE7-4BA8-8644-CC68D1B2B756_symbolID",
      "value": ""
    },
    {
      "_class": "overrideValue",
      "do_objectID": "18BC6426-703A-4809-9CFB-EDD2731F9828",
      "overrideName": "A43B67C5-5300-4B24-AF6F-24C54043E2F9_stringValue",
      "value": "Login to Pyramid"
    }
  ],
  "resizingConstraint": 63,
  "resizingType": 0,
  "rotation": 0,
  "scale": 1,
  "shouldBreakMaskChain": false,
  "style": {
    "_class": "style",
    "do_objectID": "B6201DB6-8C2A-4179-A631-7275AE0DB7CC",
    "endMarkerType": 0,
    "miterLimit": 10,
    "startMarkerType": 0,
    "windingRule": 1
  },
  "symbolID": "755A20B5-7EA6-451D-9287-079ABC6B13C7",
  "verticalSpacing": 0
}