{
  "_class": "symbolInstance",
  "booleanOperation": 0,
  "clippingMaskMode": 0,
  "do_objectID": "0B518197-29D3-4405-9397-CFAF54B0864F",
  "exportOptions": {
    "_class": "exportOptions",
    "exportFormats": [
    ],
    "includedLayerIds": [
    ],
    "layerOptions": 0,
    "shouldTrim": false
  },
  "frame": {
    "_class": "rect",
    "constrainProportions": false,
    "height": 31,
    "width": 30,
    "x": 501,
    "y": 1203
  },
  "hasClippingMask": false,
  "horizontalSpacing": 0,
  "isFixedToViewport": false,
  "isFlippedHorizontal": false,
  "isFlippedVertical": false,
  "isLocked": false,
  "isVisible": true,
  "layerListExpandedType": 0,
  "name": "5 copy 5",
  "nameIsFixed": true,
  "overrideValues": [
    {
      "_class": "overrideValue",
      "overrideName": "15EBCCD2-7788-412C-A5D0-055DBD68E8AA_stringValue",
      "value": "5"
    },
    {
      "_class": "overrideValue",
      "do_objectID": "D604ED76-B47C-44AA-A5EF-8268B53C4DD8",
      "overrideName": "098F1000-E00D-49CE-BFBE-66FC2858882B_stringValue",
      "value": "7"
    }
  ],
  "resizingConstraint": 63,
  "resizingType": 0,
  "rotation": 0,
  "scale": 1,
  "shouldBreakMaskChain": false,
  "style": {
    "_class": "style",
    "endMarkerType": 0,
    "miterLimit": 10,
    "startMarkerType": 0,
    "windingRule": 1
  },
  "symbolID": "F897AABD-3399-4F4D-88DF-9FD076634155",
  "userInfo": {
    "com.animaapp.stc-sketch-plugin": {
      "kModelPropertiesKey": {
      }
    }
  },
  "verticalSpacing": 0
}