{
  "_class": "symbolInstance",
  "booleanOperation": 0,
  "clippingMaskMode": 0,
  "do_objectID": "689436A7-729B-403A-BC6F-BF54774A4E36",
  "exportOptions": {
    "_class": "exportOptions",
    "exportFormats": [
    ],
    "includedLayerIds": [
    ],
    "layerOptions": 0,
    "shouldTrim": false
  },
  "frame": {
    "_class": "rect",
    "constrainProportions": false,
    "do_objectID": "714C58B0-E604-4E2F-A298-448B593ABFF1",
    "height": 75,
    "width": 565,
    "x": 106,
    "y": 1635
  },
  "hasClippingMask": false,
  "horizontalSpacing": 0,
  "isFixedToViewport": false,
  "isFlippedHorizontal": false,
  "isFlippedVertical": false,
  "isLocked": false,
  "isVisible": true,
  "layerListExpandedType": 0,
  "name": "forms/input/normal copy 4",
  "nameIsFixed": false,
  "originalObjectID": "DBB6CD19-6911-4EC2-BD1B-318E20A3ECE3",
  "overrideValues": [
    {
      "_class": "overrideValue",
      "overrideName": "6D0A057F-B153-484C-BF6F-E4375743F6E7_stringValue",
      "value": " "
    },
    {
      "_class": "overrideValue",
      "overrideName": "0D85F35E-EBC8-4291-9540-52036ABA41B2_stringValue",
      "value": "Disabled form element"
    },
    {
      "_class": "overrideValue",
      "overrideName": "233ADE72-CD3A-4F27-9EED-4D204F398662_stringValue",
      "value": " "
    },
    {
      "_class": "overrideValue",
      "overrideName": "60D21749-7466-4D45-A8F4-7CEAF9140FC5_stringValue",
      "value": " "
    },
    {
      "_class": "overrideValue",
      "overrideName": "80F18796-97BB-4C24-B5E7-4A403CFCD161_stringValue",
      "value": " "
    },
    {
      "_class": "overrideValue",
      "overrideName": "712B1CDA-3608-40FC-B016-0646D16E7F9D_stringValue",
      "value": "Disabled hint text"
    }
  ],
  "resizingConstraint": 63,
  "resizingType": 0,
  "rotation": 0,
  "scale": 1,
  "shouldBreakMaskChain": false,
  "style": {
    "_class": "style",
    "do_objectID": "4EDDE8B2-C27E-4367-AB18-E1F4263CECE1",
    "endMarkerType": 0,
    "miterLimit": 10,
    "startMarkerType": 0,
    "windingRule": 1
  },
  "symbolID": "4BDEBA66-42EF-449C-A743-F7EDF21BC66E",
  "verticalSpacing": 0
}