{
  "_class": "symbolMaster",
  "allowsOverrides": true,
  "backgroundColor": {
    "_class": "color",
    "alpha": 1,
    "blue": 1,
    "green": 1,
    "red": 1
  },
  "booleanOperation": 0,
  "changeIdentifier": 5701,
  "clippingMaskMode": 0,
  "do_objectID": "E69649FF-151B-4DCB-B909-E7FC67C75A03",
  "exportOptions": {
    "_class": "exportOptions",
    "exportFormats": [
      {
        "_class": "exportFormat",
        "absoluteSize": 0,
        "fileFormat": "png",
        "name": "",
        "namingScheme": 0,
        "scale": 1,
        "visibleScaleType": 0
      }
    ],
    "includedLayerIds": [
    ],
    "layerOptions": 0,
    "shouldTrim": false
  },
  "frame": {
    "_class": "rect",
    "constrainProportions": false,
    "height": 75,
    "width": 565,
    "x": 5633,
    "y": 1750
  },
  "grid": {
    "_class": "simpleGrid",
    "gridSize": 5,
    "isEnabled": false,
    "thickGridTimes": 1
  },
  "groupLayout": {
    "_class": "MSImmutableFreeformGroupLayout"
  },
  "hasBackgroundColor": true,
  "hasClickThrough": true,
  "hasClippingMask": false,
  "horizontalRulerData": {
    "_class": "rulerData",
    "base": -180,
    "guides": [
      180,
      205,
      270,
      295,
      360,
      385,
      450,
      540,
      565,
      630,
      655,
      720,
      745,
      835,
      900,
      925,
      990,
      1015,
      1080,
      1105,
      1195,
      1260,
      475,
      810,
      1170,
      1285,
      733,
      193,
      1272,
      462,
      1003
    ]
  },
  "includeBackgroundColorInExport": true,
  "includeBackgroundColorInInstance": false,
  "includeInCloudUpload": true,
  "isFixedToViewport": false,
  "isFlippedHorizontal": false,
  "isFlippedVertical": false,
  "isFlowHome": false,
  "isLocked": false,
  "isVisible": true,
  "layerListExpandedType": 2,
  "layers": [
    {
      "class": "group",
      "id": "42BF23B6-3BFD-438B-9CAA-6D56CA587C31"
    },
    {
      "class": "symbolInstance",
      "id": "28BBD2C2-4CE2-4E97-8256-4877E3453F45"
    },
    {
      "class": "text",
      "id": "98455E2E-4828-4D31-B51A-85382D74AAEA"
    },
    {
      "class": "text",
      "id": "5446C1CF-75BB-4602-84AC-EC41E2AFC064"
    },
    {
      "class": "text",
      "id": "12DAB627-7BED-43CF-B6CA-6363F04E1DE3"
    }
  ],
  "name": "forms/switcher/1L",
  "nameIsFixed": true,
  "originalObjectID": "97D5A98B-F763-4557-8F1E-1D0F7BD9484B",
  "overrideProperties": [
    {
      "_class": "MSImmutableOverrideProperty",
      "canOverride": true,
      "overrideName": "12DAB627-7BED-43CF-B6CA-6363F04E1DE3_stringValue"
    },
    {
      "_class": "MSImmutableOverrideProperty",
      "canOverride": true,
      "overrideName": "1A32FE7F-024A-4928-B1E6-7139CF0E4306_stringValue"
    },
    {
      "_class": "MSImmutableOverrideProperty",
      "canOverride": true,
      "overrideName": "28BBD2C2-4CE2-4E97-8256-4877E3453F45_symbolID"
    },
    {
      "_class": "MSImmutableOverrideProperty",
      "canOverride": true,
      "overrideName": "5446C1CF-75BB-4602-84AC-EC41E2AFC064_stringValue"
    },
    {
      "_class": "MSImmutableOverrideProperty",
      "canOverride": true,
      "overrideName": "98455E2E-4828-4D31-B51A-85382D74AAEA_stringValue"
    },
    {
      "_class": "MSImmutableOverrideProperty",
      "canOverride": true,
      "overrideName": "AF07C5F8-FB58-4980-8331-801ADCD40F9B_symbolID"
    }
  ],
  "resizesContent": false,
  "resizingConstraint": 63,
  "resizingType": 0,
  "rotation": 0,
  "shouldBreakMaskChain": true,
  "style": {
    "_class": "style",
    "endMarkerType": 0,
    "miterLimit": 10,
    "startMarkerType": 0,
    "windingRule": 1
  },
  "symbolID": "76502748-3A7B-4376-9DD1-129FC1F62DC8",
  "verticalRulerData": {
    "_class": "rulerData",
    "base": -25,
    "guides": [
      25,
      50,
      75,
      100
    ]
  }
}